diaspora_logger/__init__.py
diaspora_logger/credential.py
diaspora_logger/logger.py
diaspora_logger/examples/__init__.py
diaspora_logger/examples/example_consumer.py
diaspora_logger/examples/example_producer.py
diaspora_logger-0.0.8.dist-info/LICENSE
diaspora_logger-0.0.8.dist-info/METADATA
diaspora_logger-0.0.8.dist-info/WHEEL
diaspora_logger-0.0.8.dist-info/top_level.txt
diaspora_logger-0.0.8.dist-info/RECORD
