Metadata-Version: 2.1
Name: diaspora-logger
Version: 0.0.8
Summary: A Python logging library for sending logs to Diaspora Streams (Kafka)
Home-page: https://github.com/globus-labs/diaspora_logger
License: LICENSE
License-File: LICENSE
Requires-Dist: kafka-python
